Metadata-Version: 2.4
Name: llama-index-postprocessor-jinaai-rerank
Version: 0.4.1
Summary: llama-index postprocessor jinaai rerank integration
Author-email: Joan Fontanals <joan.fontanals.martinez@jina.ai>
License-Expression: MIT
License-File: LICENSE
Requires-Python: <4.0,>=3.9
Requires-Dist: llama-index-core<0.15,>=0.13.0
